tree_sitter_bsv-0.1.0.dist-info/WHEEL
tree_sitter_bsv-0.1.0.dist-info/top_level.txt
tree_sitter_bsv-0.1.0.dist-info/METADATA
tree_sitter_bsv-0.1.0.dist-info/RECORD
tree_sitter_bsv/__init__.pyi
tree_sitter_bsv/parse.py
tree_sitter_bsv/py.typed
tree_sitter_bsv/binding.c
tree_sitter_bsv/__init__.py
tree_sitter_bsv/_binding.abi3.so
