Metadata-Version: 2.4
Name: tree-sitter-bsv
Version: 0.1.0
Summary: Bluespec system verilog treesitter
Author-email: Vijayvithal <jahagirdar.vs@gmail.com>
License-Expression: MIT
Project-URL: Homepage, https://github.com/jahagirdar/bsv-treesitter.git
Project-URL: Funding, https://github.com/jahagirdar/bsv-treesitter.git
Keywords: incremental,parsing,tree-sitter,bsv
Classifier: Intended Audience :: Developers
Classifier: Topic :: Software Development :: Compilers
Classifier: Topic :: Text Processing :: Linguistic
Classifier: Typing :: Typed
Requires-Python: >=3.10
Provides-Extra: core
Requires-Dist: tree-sitter~=0.24; extra == "core"
